{"Category":"Sức khỏe","CategoryUrl":null,"CategoryPublishedContent":null,"Author":"\n                                            NGUYỄN THẠNH","Source":"NLD","SourceUrl":" https://nld.com.vn/suc-khoe/benh-vien-cho-ray-dua-vao-hoat-dong-trung-tam-hoi-chan-tu-van-kham-chua-benh-tu-xa-20200923120849006.htm ","Title":" Bệnh viện Chợ Rẫy đưa vào hoạt động Trung tâm Hội chẩn tư vấn, khám chữa bệnh từ xa ","ShortDescription":"\n                                (NLĐO) - Việc đưa vào hoạt động Trung tâm Hội chẩn tư vấn, khám chữa bệnh từ xa tại Bệnh viện Chợ Rẫy mang lại nhiều lợi ích cho người bệnh: kịp thời được xử lý trong tình huống khẩn cấp, tiết kiệm thời gian, chi phí\n                            ","FullDescription":"<div class=\"contentbody\" id=\"content-id\">\n\n                                        <div class=\"clearfix\"></div>\n                                        <div data-check-position=\"autopro_detail_position_start\"></div>\n                                        <div class=\"content-news-detail old-news\" data-field=\"body\">\n                                            <p>Sáng 23-9, Bệnh viện <a href=\"https://nld.com.vn/cho-ray.html\" title=\"Chợ Rẫy\" target=\"_blank\">Chợ Rẫy</a> đã đưa vào hoạt động Trung tâm Hội chẩn tư vấn, khám chữa bệnh từ xa. Đây là một trong những hoạt động thuộc đề án Khám chữa bệnh từ xa giai đoạn 2020 - 2025 của Bộ Y tế.<br></p><p>Thầy thuốc ưu tú BS CK2 Nguyễn Tri Thức, Giám đốc Bệnh viện <a href=\"https://nld.com.vn/cho-ray.html\" title=\"Chợ Rẫy\" target=\"_blank\">Chợ Rẫy</a>, cho biết mỗi ngày bệnh viện khám và điều trị cho gần 10.000 lượt bệnh nhân nội và ngoại trú, đặc biệt trong đó có rất nhiều bệnh nhân nặng được chuyển lên từ các tuyến.&nbsp;</p><p>Chỉ tính riêng trong 6 tháng đầu năm có hơn 26.500 bệnh nhân từ các tỉnh thành được chuyển đến Khoa Cấp cứu của Bệnh viện <a href=\"https://nld.com.vn/cho-ray.html\" title=\"Chợ Rẫy\" target=\"_blank\">Chợ Rẫy</a>. Bên cạnh nguy cơ mất an toàn do bệnh lý trong quá trình vận chuyển, người bệnh còn có thể đối diện với rất nhiều khó khăn và tốn kém.  </p><div class=\"VCSortableInPreviewMode\" type=\"Photo\"><div><img src=\"https://nld.mediacdn.vn/thumb_w/684/2020/9/23/p20200923104255-1600837192194944863313.jpg\" id=\"img_9afb0440-fd59-11ea-a42f-9f403806d2ae\" w=\"1920\" h=\"1080\" alt=\"Bệnh viện Chợ Rẫy đưa vào hoạt động Trung tâm Hội chẩn tư vấn, khám chữa bệnh từ xa - Ảnh 1.\" title=\"Bệnh viện Chợ Rẫy đưa vào hoạt động Trung tâm Hội chẩn tư vấn, khám chữa bệnh từ xa - Ảnh 1.\" rel=\"lightbox\" photoid=\"9afb0440-fd59-11ea-a42f-9f403806d2ae\" type=\"photo\" style=\"max-width:100%;\" data-original=\"https://nld.mediacdn.vn/2020/9/23/p20200923104255-1600837192194944863313.jpg\" width=\"\" height=\"\"></div><div class=\"PhotoCMS_Caption\"><p data-placeholder=\"[nhập chú thích]\" class=\"\">Trung tâm Hội chẩn tư vấn, khám chữa bệnh từ xa Bệnh viện <a href=\"https://nld.com.vn/cho-ray.html\" title=\"Chợ Rẫy\" target=\"_blank\">Chợ Rẫy</a> đưa vào hoạt động sáng nay</p></div></div><div id=\"admsection2\"></div><p>Là bệnh viện tuyến cuối hạng đặc biệt trực thuộc Bộ Y tế, ngoài chức năng điều trị và hỗ trợ điều trị cho các tỉnh thành phía Nam, Bệnh viện <a href=\"https://nld.com.vn/cho-ray.html\" title=\"Chợ Rẫy\" target=\"_blank\">Chợ Rẫy</a> thường xuyên kích hoạt các chương trình báo động đỏ và quy trình vàng nhằm hỗ trợ các đơn vị bạn cũng như các bệnh viện tuyến địa phương hội chẩn từ xa.&nbsp;</p><div id=\"admsection3\"></div><p>Với ý nghĩa đó, Bệnh viện <a href=\"https://nld.com.vn/cho-ray.html\" title=\"Chợ Rẫy\" target=\"_blank\">Chợ Rẫy</a> phối hợp cùng Tổng công ty giải pháp doanh nghiệp Viettel đưa vào hoạt động Trung tâm Hội chẩn tư vấn, khám chữa bệnh từ xa bệnh viện <a href=\"https://nld.com.vn/cho-ray.html\" title=\"Chợ Rẫy\" target=\"_blank\">Chợ Rẫy</a>. Với công nghệ truyền dẫn hình ảnh hiện đại, hệ thống này là một trong những giải pháp tối ưu không chỉ lưu trữ và bảo mật các thông tin cá nhân của người bệnh mà còn giúp các bác sĩ có thể hội chẩn và đưa ra hướng điều trị ngay trên hệ thống.  </p><p>TS Cao Hưng Thái, Phó Cục trưởng Cục Khám, chữa bệnh-Bộ Y tế, cho biết cả nước đến nay đã có 26 bệnh viện tuyến cuối lập trung tâm chẩn bệnh từ xa với hơn 1.000 điểm cầu. Việc đưa vào hoạt động Trung tâm Hội chẩn tư vấn, khám chữa bệnh từ xa tại Bệnh viện Chợ Rẫy không chỉ mang lại nhiều lợi ích cho người bệnh như kịp thời được xử lý trong tình huống khẩn cấp, an toàn hiệu quả ngay ở tuyến dưới, tiết kiệm thời gian, chi phí điều trị… mà còn góp phần nâng cao chất lượng điều trị cho các bệnh viện tuyến địa phương, gia tăng cơ hội cho người bệnh ở vùng sâu, vùng xa được tiếp cận các kỹ thuật, phương pháp hiện đại trong chẩn đoán và điều trị. </p><p>Ngay sau sự kiện khai trương, Trung tâm Hội chẩn tư vấn, khám chữa bệnh từ xa Bệnh viện Chợ Rẫy phối hợp hội chẩn cho 3 bệnh nhân tại 3 đầu cầu gồm Trung tâm y tế quân dân y huyện Côn Đảo (Bà Rịa - Vũng Tàu), Bệnh viện Đa khoa Cà Mau và Bệnh viện Đa khoa Bình Định.  </p>\n                                            <!-- Bắt đầu Dable / Để được giải đáp, hãy truy cập http://dable.io -->\n                                            \n                                            <!-- Kết thúc / Để được giải đáp, hãy truy cập http://dable.io -->\n                                        </div>\n\n                                        <span class=\"author fr\" data-field=\"author\">\n                                            NGUYỄN THẠNH</span>\n                                        <div class=\"clearfix\"></div>\n                                        <div class=\"sharemxh bottomshare\">\n                                            <div class=\"fb\">\n                                                <a onclick=\"fbClient.shareClick('https://nld.com.vn/news-20200923120849006.htm');\" href=\"javascript:;\" class=\"kbwcs-fb fl\" rel=\"nofollow\">\n                                                    <p class=\"textshare\">Chia sẻ</p>\n                                                    <span class=\"kbwcs-number fr item-fb\" rel=\"https://nld.com.vn/news-20200923120849006.htm\"></span>\n                                                </a>\n                                                <div class=\"fb-like fb_iframe_widget fl\" data-href=\"https://nld.com.vn/news-20200923120849006.htm\" data-layout=\"button_count\" data-action=\"like\" data-size=\"small\" data-show-faces=\"false\" data-share=\"false\" fb-xfbml-state=\"rendered\" fb-iframe-plugin-query=\"action=like&amp;app_id=115279665149396&amp;container_width=85&amp;href=https://nld.com.vn/news-20200923120849006.htm&amp;layout=button_count&amp;locale=vi_VN&amp;sdk=joey&amp;share=false&amp;show_faces=false&amp;size=small\">\n                                                </div>\n                                            </div>\n                                            \n                                            <div class=\"zalo\">\n                                                <div class=\"zalomagazine\">\n                                                    <div class=\"zalo-share-button\" data-href=\"https://nld.com.vn/news-20200923120849006.htm\" data-oaid=\"3913620002469723939\" data-layout=\"2\" data-color=\"blue\" data-customize=\"false\"></div>\n                                                </div>\n                                                <script async=\"\" src=\"https://sp.zalo.me/plugins/sdk.js\"></script>\n                                            </div>\n                                            <div class=\"print\">\n                                                <a target=\"_blank\" title=\"Print\" href=\"/Print.aspx?NewsID=20200923120849006\" rel=\"nofollow\">\n                                                    <img src=\"https://nld.mediacdn.vn/web_images/icon-print-3.png\" class=\"iconprintdetailbot\">\n                                                </a>\n                                            </div>\n                                            <div class=\"clear-both\"></div>\n                                        </div>\n                                    </div>","Picture":"benh-vien-cho-ray-dua-vao-hoat-dong-trung-tam-hoi-chan-tu-van-kham-chua-benh-tu-xa-20200923120849006","PostedDateTime":"09/23/2020 12:21:38 PM","PostedTime":null,"Location":null,"DescriptionSuffix":null,"RelatedNewsModel":[],"PictureUrl":null,"PictureName":"benh-vien-cho-ray-dua-vao-hoat-dong-trung-tam-hoi-chan-tu-van-kham-chua-benh-tu-xa-20200923120849006.jpg","PictureExternalUrl":"https://nld.mediacdn.vn/zoom/600_315/2020/9/23/p20200923105209-16008374848311320958190.jpg","HashContent":null,"Id":0,"DocumentType":null,"Name":"benh-vien-cho-ray-dua-vao-hoat-dong-trung-tam-hoi-chan-tu-van-kham-chua-benh-tu-xa-20200923120849006","Path":null,"CreatedDate":"0001-01-01T00:00:00","Creator":null,"Url":" https://nld.com.vn/suc-khoe/benh-vien-cho-ray-dua-vao-hoat-dong-trung-tam-hoi-chan-tu-van-kham-chua-benh-tu-xa-20200923120849006.htm ","PublishedContent":null,"Children":null,"ParentId":1107,"MetaPageTitle":" Bệnh viện Chợ Rẫy đưa vào hoạt động Trung tâm Hội chẩn tư vấn, khám chữa bệnh từ xa ","MetaKeywords":null,"MetaDescription":null}