{"Category":"Thời sự trong nước","CategoryUrl":null,"CategoryPublishedContent":null,"Author":"\n                                            Cao Nguyên","Source":"NLD","SourceUrl":" https://nld.com.vn/thoi-su/dang-gat-lua-thi-bi-set-danh-2-nguoi-chet-1-nguoi-nguy-kich-20200922170252728.htm ","Title":" Đang gặt lúa thì bị sét đánh, 2 người chết, 1 người nguy kịch ","ShortDescription":"\n                                (NLĐO) – Trong lúc đang gặt lúa ngoài đồng, 3 người dân không may bị sét đánh trúng khiến 2 người tử vong, một người may mắn được cứu sống.\n                            ","FullDescription":"<div class=\"contentbody\" id=\"content-id\">\n\n                                        <div class=\"clearfix\"></div>\n                                        <div data-check-position=\"autopro_detail_position_start\"></div>\n                                        <div class=\"content-news-detail old-news\" data-field=\"body\">\n                                            <p>Chiều 22-9, Trung tâm Y tế huyện Cư M’gar, tỉnh Đắk Lắk cho biết đơn vị vừa tiếp nhận 3 trường hợp bị <a href=\"https://nld.com.vn/set-danh.html\" title=\"sét đánh\" target=\"_blank\">sét đánh</a> nhưng 2 người đã tử vong<br></p><div class=\"VCSortableInPreviewMode active\" type=\"Photo\"><div><img src=\"https://nld.mediacdn.vn/thumb_w/684/2020/9/22/119936726628827661117096807116385772195285n-16007687518641718419090.jpg\" id=\"img_43e37c40-fcba-11ea-aa4e-af186a481c6a\" w=\"960\" h=\"540\" alt=\"Đang gặt lúa thì bị sét đánh, 2 người chết, 1 người nguy kịch - Ảnh 1.\" title=\"Đang gặt lúa thì bị sét đánh, 2 người chết, 1 người nguy kịch - Ảnh 1.\" rel=\"lightbox\" photoid=\"43e37c40-fcba-11ea-aa4e-af186a481c6a\" type=\"photo\" data-original=\"https://nld.mediacdn.vn/2020/9/22/119936726628827661117096807116385772195285n-16007687518641718419090.jpg\" width=\"\" height=\"\"></div><div class=\"PhotoCMS_Caption\"><p data-placeholder=\"[nhập chú thích]\" class=\"\">Em Y L. may mắn được cứu sống</p></div></div><div id=\"admsection2\"></div><p>Theo thông tin ban đầu, trưa cùng ngày Trung tâm Y tế huyện Cư M’gar tiếp nhận 3 bệnh nhân gồm: Y L. (SN 2006) Y S. (SN 1988, dượng của Y L.) và Y T. (SN 1980, cậu của Y S., cùng ngụ xã Cư M’gar, huyện Cư M’gar) trong tình trạng ngưng tim, ngưng thở.  </p><p>Ngay lập tức các bác sĩ đã tiến hành cấp cứu. Sau khoảng 10 phút, tim bệnh nhân Y L. đập trở lại và huyết áp đo được. Riêng 2 bệnh nhân Y T. và Y S. được xác định đã tử vong ngoại viện.  </p><div id=\"admsection3\"></div><p>Theo các bác sĩ, hiện tại chỉ số sinh tồn của bệnh nhân Y L. ổn định. Tuy nhiên, do bị chấn động não nên bệnh nhân thường xuyên xuất hiện cơn kích thích, hoảng loạn.  </p><p>Theo người nhà cháu Y L, vào trưa cùng ngày cả 3 cùng một số người đi gặt lúa ngoài đồng thì trời mưa giông. Đến khoảng 12 giờ 40 phút cùng ngày, Y L., Y S. và Y T. đang vác lúa từ bờ ruộng lên xe, đi theo hàng dọc thì bất ngờ bị sét đánh dẫn đến bất tỉnh. Mọi người lập tức đưa 3 nạn nhân đến bệnh viện cấp cứu nhưng 2 người đã tử vong.  </p>\n\n                                            <!-- Bắt đầu Dable / Để được giải đáp, hãy truy cập http://dable.io -->\n                                            \n                                            <!-- Kết thúc / Để được giải đáp, hãy truy cập http://dable.io -->\n                                        </div>\n\n                                        <span class=\"author fr\" data-field=\"author\">\n                                            Cao Nguyên</span>\n                                        <div class=\"clearfix\"></div>\n                                        <div class=\"sharemxh bottomshare\">\n                                            <div class=\"fb\">\n                                                <a onclick=\"fbClient.shareClick('https://nld.com.vn/news-20200922170252728.htm');\" href=\"javascript:;\" class=\"kbwcs-fb fl\" rel=\"nofollow\">\n                                                    <p class=\"textshare\">Chia sẻ</p>\n                                                    <span class=\"kbwcs-number fr item-fb\" rel=\"https://nld.com.vn/news-20200922170252728.htm\"></span>\n                                                </a>\n                                                <div class=\"fb-like fb_iframe_widget fl\" data-href=\"https://nld.com.vn/news-20200922170252728.htm\" data-layout=\"button_count\" data-action=\"like\" data-size=\"small\" data-show-faces=\"false\" data-share=\"false\" fb-xfbml-state=\"rendered\" fb-iframe-plugin-query=\"action=like&amp;app_id=115279665149396&amp;container_width=85&amp;href=https://nld.com.vn/news-20200922170252728.htm&amp;layout=button_count&amp;locale=vi_VN&amp;sdk=joey&amp;share=false&amp;show_faces=false&amp;size=small\">\n                                                </div>\n                                            </div>\n                                            \n                                            <div class=\"zalo\">\n                                                <div class=\"zalomagazine\">\n                                                    <div class=\"zalo-share-button\" data-href=\"https://nld.com.vn/news-20200922170252728.htm\" data-oaid=\"3913620002469723939\" data-layout=\"2\" data-color=\"blue\" data-customize=\"false\"></div>\n                                                </div>\n                                                <script async=\"\" src=\"https://sp.zalo.me/plugins/sdk.js\"></script>\n                                            </div>\n                                            <div class=\"print\">\n                                                <a target=\"_blank\" title=\"Print\" href=\"/Print.aspx?NewsID=20200922170252728\" rel=\"nofollow\">\n                                                    <img src=\"https://nld.mediacdn.vn/web_images/icon-print-3.png\" class=\"iconprintdetailbot\">\n                                                </a>\n                                            </div>\n                                            <div class=\"clear-both\"></div>\n                                        </div>\n                                    </div>","Picture":"dang-gat-lua-thi-bi-set-danh-2-nguoi-chet-1-nguoi-nguy-kich-20200922170252728","PostedDateTime":"09/22/2020 6:01:20 PM","PostedTime":null,"Location":null,"DescriptionSuffix":null,"RelatedNewsModel":[],"PictureUrl":null,"PictureName":"dang-gat-lua-thi-bi-set-danh-2-nguoi-chet-1-nguoi-nguy-kich-20200922170252728.jpg","PictureExternalUrl":"https://nld.mediacdn.vn/zoom/600_315/2020/9/22/119936726628827661117096807116385772195285n-16007687518641718419090.jpg","HashContent":null,"Id":0,"DocumentType":null,"Name":"dang-gat-lua-thi-bi-set-danh-2-nguoi-chet-1-nguoi-nguy-kich-20200922170252728","Path":null,"CreatedDate":"0001-01-01T00:00:00","Creator":null,"Url":" https://nld.com.vn/thoi-su/dang-gat-lua-thi-bi-set-danh-2-nguoi-chet-1-nguoi-nguy-kich-20200922170252728.htm ","PublishedContent":null,"Children":null,"ParentId":1107,"MetaPageTitle":" Đang gặt lúa thì bị sét đánh, 2 người chết, 1 người nguy kịch ","MetaKeywords":null,"MetaDescription":null}